datacompy/__init__.py
datacompy/base.py
datacompy/core.py
datacompy/fugue.py
datacompy/polars.py
datacompy/py.typed
datacompy/snowflake.py
datacompy/utility.py
datacompy/spark/__init__.py
datacompy/spark/helper.py
datacompy/spark/sql.py
datacompy/templates/column_comparison.txt
datacompy/templates/column_summary.txt
datacompy/templates/header.txt
datacompy/templates/report_template.j2
datacompy/templates/row_summary.txt
datacompy-0.19.2.dist-info/licenses/LICENSE
datacompy-0.19.2.dist-info/METADATA
datacompy-0.19.2.dist-info/WHEEL
datacompy-0.19.2.dist-info/top_level.txt
datacompy-0.19.2.dist-info/RECORD
