Metadata-Version: 2.4
Name: datacompy
Version: 0.19.2
Summary: Dataframe comparison in Python
Author-email: Faisal Dosani <faisal.dosani@capitalone.com>, Raymond Haffar <raymond.haffar@capitalone.com>, Jacob Dawang <jacob.dawang@capitalone.com>
Maintainer-email: Faisal Dosani <faisal.dosani@capitalone.com>, Jacob Dawang <jacob.dawang@capitalone.com>, Raymond Haffar <raymond.haffar@capitalone.com>
License: Apache Software License
Project-URL: Bug Tracker, https://github.com/capitalone/datacompy/issues
Project-URL: Documentation, https://capitalone.github.io/datacompy/
Project-URL: Homepage, https://github.com/capitalone/datacompy
Project-URL: Repository, https://github.com/capitalone/datacompy.git
Project-URL: Source Code, https://github.com/capitalone/datacompy
Classifier: Intended Audience :: Developers
Classifier: Natural Language :: English
Classifier: Operating System :: OS Independent
Classifier: Programming Language :: Python
Classifier: Programming Language :: Python :: 3 :: Only
Classifier: Programming Language :: Python :: 3.10
Classifier: Programming Language :: Python :: 3.11
Classifier: Programming Language :: Python :: 3.12
Classifier: Programming Language :: Python :: 3.13
Requires-Python: >=3.10.0
License-File: LICENSE
Requires-Dist: jinja2>=3
Requires-Dist: numpy<=2.3.5,>=1.26
Requires-Dist: ordered-set<=4.1,>=4.0.2
Requires-Dist: pandas<=2.3.3,>=2.2
Requires-Dist: polars[pandas]<=1.36.1,>=0.20.4
Provides-Extra: build
Requires-Dist: build; extra == "build"
Requires-Dist: twine; extra == "build"
Requires-Dist: wheel; extra == "build"
Provides-Extra: dev
Requires-Dist: datacompy[build]; extra == "dev"
Requires-Dist: datacompy[docs]; extra == "dev"
Requires-Dist: datacompy[fugue]; extra == "dev"
Requires-Dist: datacompy[qa]; extra == "dev"
Requires-Dist: datacompy[snowflake]; extra == "dev"
Requires-Dist: datacompy[spark]; extra == "dev"
Requires-Dist: datacompy[tests-snowflake]; extra == "dev"
Requires-Dist: datacompy[tests-spark]; extra == "dev"
Requires-Dist: datacompy[tests]; extra == "dev"
Provides-Extra: dev-no-snowflake
Requires-Dist: datacompy[build]; extra == "dev-no-snowflake"
Requires-Dist: datacompy[docs]; extra == "dev-no-snowflake"
Requires-Dist: datacompy[fugue]; extra == "dev-no-snowflake"
Requires-Dist: datacompy[qa]; extra == "dev-no-snowflake"
Requires-Dist: datacompy[spark]; extra == "dev-no-snowflake"
Requires-Dist: datacompy[tests-spark]; extra == "dev-no-snowflake"
Requires-Dist: datacompy[tests]; extra == "dev-no-snowflake"
Provides-Extra: docs
Requires-Dist: furo; extra == "docs"
Requires-Dist: myst-parser; extra == "docs"
Requires-Dist: sphinx; extra == "docs"
Provides-Extra: edgetest
Requires-Dist: edgetest; extra == "edgetest"
Requires-Dist: edgetest-conda; extra == "edgetest"
Provides-Extra: fugue
Requires-Dist: duckdb<1.4; extra == "fugue"
Requires-Dist: fugue[dask,duckdb,ray]<=0.9.1,>=0.8.7; extra == "fugue"
Provides-Extra: qa
Requires-Dist: mypy; extra == "qa"
Requires-Dist: pandas-stubs; extra == "qa"
Requires-Dist: pre-commit; extra == "qa"
Requires-Dist: ruff==0.5.7; extra == "qa"
Provides-Extra: snowflake
Requires-Dist: snowflake-connector-python; extra == "snowflake"
Requires-Dist: snowflake-snowpark-python; extra == "snowflake"
Provides-Extra: spark
Requires-Dist: pyspark[connect]<=3.5.6,>=3.4; extra == "spark"
Provides-Extra: tests
Requires-Dist: pytest; extra == "tests"
Requires-Dist: pytest-cov; extra == "tests"
Provides-Extra: tests-snowflake
Requires-Dist: snowflake-snowpark-python[localtest]; extra == "tests-snowflake"
Provides-Extra: tests-spark
Requires-Dist: pytest; extra == "tests-spark"
Requires-Dist: pytest-cov; extra == "tests-spark"
Requires-Dist: pytest-spark; extra == "tests-spark"
Dynamic: license-file
